{
  "kind": "singleType",
  "collectionName": "about_uses",
  "info": {
    "singularName": "about-us",
    "pluralName": "about-uses",
    "displayName": "About Us",
    "description": ""
  },
  "options": {
    "draftAndPublish": true
  },
  "pluginOptions": {},
  "attributes": {
    "Top_Banner_Heading": {
      "type": "string"
    },
    "Banner_Image": {
      "type": "media",
      "multiple": false,
      "required": false,
      "allowedTypes": [
        "images",
        "files",
        "videos",
        "audios"
      ]
    },
    "Our_Culture_Heading": {
      "type": "string"
    },
    "Our_Culture_Banner": {
      "type": "media",
      "multiple": false,
      "required": false,
      "allowedTypes": [
        "images",
        "files",
        "videos",
        "audios"
      ]
    },
    "Left_Image": {
      "type": "media",
      "multiple": false,
      "required": false,
      "allowedTypes": [
        "images",
        "files",
        "videos",
        "audios"
      ]
    },
    "Right_Image": {
      "type": "media",
      "multiple": false,
      "required": false,
      "allowedTypes": [
        "images",
        "files",
        "videos",
        "audios"
      ]
    },
    "Carrer_Section_Image": {
      "type": "media",
      "multiple": false,
      "required": false,
      "allowedTypes": [
        "images",
        "files",
        "videos",
        "audios"
      ]
    },
    "Career_Button": {
      "type": "text"
    },
    "Url": {
      "type": "string"
    },
    "Left_Content": {
      "type": "customField",
      "options": {
        "preset": "toolbar"
      },
      "customField": "plugin::ckeditor5.CKEditor"
    },
    "Right_Content": {
      "type": "customField",
      "options": {
        "preset": "toolbar"
      },
      "customField": "plugin::ckeditor5.CKEditor"
    }
  }
}
